doc.ini
setup.py
pastables/__init__.py
pastables/domain.py
pastables/file_logger.py
pastables/force_content_type.py
pastables/garbage_collection.py
pastables/htmltxt.py
pastables/imglink.py
pastables/query_string.py
pastables/redirect.py
pastables/remote_user.py
pastables/request_logger.py
pastables/request_method.py
pastables/rewrite_location_header.py
pastables/wsgi_filter.py
pastables.egg-info/PKG-INFO
pastables.egg-info/SOURCES.txt
pastables.egg-info/dependency_links.txt
pastables.egg-info/entry_points.txt
pastables.egg-info/not-zip-safe
pastables.egg-info/requires.txt
pastables.egg-info/top_level.txt