Metadata-Version: 1.0
Name: pastables
Version: 0.0
Summary: Assorted building blocks for WSGI applications using paste and webob
Home-page: http://github.com/ejucovy/pastables
Author: Ethan Jucovy
Author-email: ethan.jucovy@gmail.com
License: UNKNOWN
Platform: UNKNOWN
